petit_recipe_executor/__init__.py
petit_recipe_executor/context.py
petit_recipe_executor/datastruct.py
petit_recipe_executor/executor.py
petit_recipe_executor/utils.py
petit_recipe_executor/base_functions/__init__.py
petit_recipe_executor/base_functions/base_functions.py
petit_recipe_executor/base_functions/http_funcs.py
petit_recipe_executor/tests/__init__.py
petit_recipe_executor/tests/test_executor.py
petit_recipe_executor-0.1.0.dist-info/METADATA
petit_recipe_executor-0.1.0.dist-info/WHEEL
petit_recipe_executor-0.1.0.dist-info/top_level.txt
petit_recipe_executor-0.1.0.dist-info/RECORD
