Metadata-Version: 2.1
Name: petit-recipe-executor
Version: 0.1.0
Summary: Execute simple recipes to test small things
Home-page: https://github.com/Plawn/petit_recipe_executor
Author: Plawn
Author-email: plawn.yay@gmail.com
License: apache-2.0
Platform: UNKNOWN
Requires-Python: >=3.8
Requires-Dist: requests
Requires-Dist: pydantic
